{"literal": "動", "radical": 19, "grade": 3, "jouyou": true, "strokeCount": 11, "on": ["ドウ"], "kun": ["うご.く", "うご.かす"], "meanings": ["move", "motion", "change", "confusion", "shift", "shake"], "compounds": [{"readings": ["いどう"], "meanings": ["change (personnel)", "transfer", "reshuffle"], "word": "異動"}, {"readings": ["いどう"], "meanings": ["movement", "transfer", "migration", "removal", "travel", "mobile", "moving", "traveling", "travelling", "roving"], "word": "移動"}, {"readings": ["うんどう"], "meanings": ["exercise", "physical training", "work-out", "appeal", "campaign", "drive", "crusade", "movement", "lobbying", "motion", "movement"], "word": "運動"}, {"readings": ["うんどうかい"], "meanings": ["athletic meet (esp. at school)", "sports day"], "word": "運動会"}, {"readings": ["うんどうじょう", "うんどうば"], "meanings": ["sports ground", "playing field", "playground"], "word": "運動場"}, {"readings": ["うんどうしんけい"], "meanings": ["motor nerves", "reflexes"], "word": "運動神経"}, {"readings": ["うんどうひ"], "meanings": ["campaign fund"], "word": "運動費"}, {"readings": ["うんどうぶそく"], "meanings": ["lack of physical exercise", "insufficient exercise", "inactivity"], "word": "運動不足"}, {"readings": ["かどう"], "meanings": ["mobile", "moveable"], "word": "可動"}, {"readings": ["にうごき"], "meanings": ["movement of goods"], "word": "荷動き"}, {"readings": ["かつどう"], "meanings": ["activity (of a person, organization, animal, volcano, etc.)", "action", "movie (esp. during the silent movie period)"], "word": "活動"}, {"readings": ["かつどうか"], "meanings": ["activist"], "word": "活動家"}, {"readings": ["かんどうみゃく"], "meanings": ["coronary artery"], "word": "冠動脈"}, {"readings": ["かんどう"], "meanings": ["being deeply moved emotionally", "excitement", "passion", "inspiration", "deep emotion", "strong impression"], "word": "感動"}, {"readings": ["きどう"], "meanings": ["maneuver (usu. of military force)", "manoeuvre", "mobile", "nimble", "agile", "quick to respond"], "word": "機動"}, {"readings": ["きどうたい"], "meanings": ["riot police", "riot squad"], "word": "機動隊"}, {"readings": ["きどう"], "meanings": ["startup", "booting up", "activation", "starting (e.g. engine, computer)", "launch"], "word": "起動"}, {"readings": ["きょどう"], "meanings": ["conduct", "behavior", "behaviour"], "word": "挙動"}, {"readings": ["くどう"], "meanings": ["driving force"], "word": "駆動"}, {"readings": ["げきどう"], "meanings": ["violent shock", "agitation", "turbulence", "turmoil", "upheaval", "excitement"], "word": "激動"}, {"readings": ["げんどうき"], "meanings": ["motor"], "word": "原動機"}, {"readings": ["げんどうりょく"], "meanings": ["motive power", "driving force"], "word": "原動力"}, {"readings": ["げんどう"], "meanings": ["speech and conduct", "words and deeds"], "word": "言動"}, {"readings": ["こどう"], "meanings": ["beat", "palpitation", "pulsation", "throbbing"], "word": "鼓動"}, {"readings": ["こうどう"], "meanings": ["action", "conduct", "behaviour", "behavior", "mobilization", "mobilisation"], "word": "行動"}, {"readings": ["さいきどう"], "meanings": ["restart", "reboot"], "word": "再起動"}, {"readings": ["さどう"], "meanings": ["operation", "functioning", "running"], "word": "作動"}, {"readings": ["しどう"], "meanings": ["starting (machine, engine, car, etc.)", "activation"], "word": "始動"}, {"readings": ["じどう"], "meanings": ["automatic", "intransitive verb"], "word": "自動"}, {"readings": ["じどうか"], "meanings": ["automation"], "word": "自動化"}, {"readings": ["じどうしゃ"], "meanings": ["automobile", "motorcar", "motor vehicle", "car", "auto"], "word": "自動車"}, {"readings": ["じどうてき"], "meanings": ["automatic"], "word": "自動的"}, {"readings": ["じどうはんばいき"], "meanings": ["vending machine"], "word": "自動販売機"}, {"readings": ["しゅどう"], "meanings": ["manual (operation)"], "word": "手動"}, {"readings": ["じゅどう"], "meanings": ["passivity"], "word": "受動"}, {"readings": ["じゅどうてき"], "meanings": ["passive"], "word": "受動的"}, {"readings": ["しゅつどう"], "meanings": ["sailing", "marching", "going out", "dispatch"], "word": "出動"}, {"readings": ["しょうどう"], "meanings": ["impulse", "impetus", "urge"], "word": "衝動"}, {"readings": ["じょうげどう"], "meanings": ["vertical motion (in earthquakes)"], "word": "上下動"}, {"readings": ["しんどう"], "meanings": ["oscillation", "vibration", "swing (e.g. of a pendulum)"], "word": "振動"}, {"readings": ["しんどう"], "meanings": ["shock", "tremor", "impact", "vibration"], "word": "震動"}, {"readings": ["じんじいどう"], "meanings": ["personnel change", "personnel shift", "reshuffle", "(annual) staff reassignment"], "word": "人事異動"}, {"readings": ["せいどう"], "meanings": ["braking (mechanism)"], "word": "制動"}, {"readings": ["せんどう"], "meanings": ["incitement", "sedition", "agitation", "abetting"], "word": "扇動"}, {"readings": ["そうどう"], "meanings": ["strife", "riot", "rebellion", "turmoil", "(media) uproar", "brouhaha", "(public) outcry", "scandal", "controversy", "feud", "tussle", "quarrel", "dispute"], "word": "騒動"}, {"readings": ["たいどう"], "meanings": ["quickening", "foetal (fetal) movement", "fomenting (trouble)"], "word": "胎動"}, {"readings": ["ちかくへんどう"], "meanings": ["diastrophism", "movement and deformation of the earth's crust", "upheaval (e.g. in politics)", "seismic shift", "earthshaking changes"], "word": "地殻変動"}, {"readings": ["ちょくせつこうどう"], "meanings": ["direct action"], "word": "直接行動"}, {"readings": ["てんどうせつ"], "meanings": ["Ptolemaic theory", "geocentric model", "geocentrism"], "word": "天動説"}, {"readings": ["でんどう"], "meanings": ["electric"], "word": "電動"}, {"readings": ["どう"], "meanings": ["motion", "change", "confusion"], "word": "動"}, {"readings": ["うごかす"], "meanings": ["to move", "to shift", "to stir", "to budge", "to change position", "to inspire", "to rouse", "to move (e.g. feeling)", "to influence", "to change", "to alter", "to deny", "to operate", "to set in motion", "to get going", "to mobilize (e.g. troops)", "to mobilise", "to deploy", "to manage (e.g. funds)"], "word": "動かす"}, {"readings": ["うごき"], "meanings": ["movement", "move", "motion", "trend", "development", "change", "fluctuation"], "word": "動き"}, {"readings": ["うごきまわる"], "meanings": ["to move around"], "word": "動き回る"}, {"readings": ["うごく"], "meanings": ["to move", "to stir", "to shift", "to shake", "to swing", "to operate", "to run", "to go", "to work", "to make a move", "to take action", "to act", "to go into action", "to be touched", "to be influenced", "to change", "to vary", "to fluctuate", "to waver", "to be transferred"], "word": "動く"}, {"readings": ["どうじる"], "meanings": ["to be perturbed", "to be agitated"], "word": "動じる"}, {"readings": ["ややもすれば"], "meanings": ["being apt to", "being liable to", "being inclined to"], "word": "動もすれば"}, {"readings": ["どういん"], "meanings": ["mobilization", "mobilisation"], "word": "動員"}, {"readings": ["どうが"], "meanings": ["video", "movie", "moving picture", "animation", "animated cartoon", "in-betweens (animation)"], "word": "動画"}, {"readings": ["どうき"], "meanings": ["motive", "incentive", "motif"], "word": "動機"}, {"readings": ["どうぎ"], "meanings": ["motion (i.e. proposal to a committee, etc.)"], "word": "動議"}, {"readings": ["どうこう"], "meanings": ["trend", "tendency", "movement", "attitude"], "word": "動向"}, {"readings": ["どうさ"], "meanings": ["action", "movements", "motions", "bearing", "behaviour", "behavior", "execution", "actuation", "operation", "manners"], "word": "動作"}, {"readings": ["どうし"], "meanings": ["verb"], "word": "動詞"}, {"readings": ["どうしょくぶつ"], "meanings": ["plants and animals", "flora and fauna"], "word": "動植物"}, {"readings": ["どうたい"], "meanings": ["movement", "dynamic state"], "word": "動態"}, {"readings": ["どうてき"], "meanings": ["dynamic", "kinetic"], "word": "動的"}, {"readings": ["どうてん"], "meanings": ["disturbance of mind", "losing one's head", "being upset", "being astonished", "being frightened", "transition", "changing", "moving"], "word": "動転"}, {"readings": ["どうぶつ"], "meanings": ["animal"], "word": "動物"}, {"readings": ["どうぶつえん"], "meanings": ["zoo", "zoological gardens"], "word": "動物園"}, {"readings": ["どうみゃく"], "meanings": ["artery"], "word": "動脈"}, {"readings": ["どうみゃくこうか"], "meanings": ["arteriosclerosis", "hardening of the arteries"], "word": "動脈硬化"}, {"readings": ["どうよう"], "meanings": ["shaking", "trembling", "pitching", "rolling", "oscillation", "disturbance", "unrest", "agitation", "excitement", "commotion", "turmoil", "discomposure", "feeling shaken"], "word": "動揺"}, {"readings": ["どうらん"], "meanings": ["disturbance", "agitation", "commotion", "upheaval", "riot"], "word": "動乱"}, {"readings": ["どうりょく"], "meanings": ["power", "motive power", "dynamic force", "three-phase electricity"], "word": "動力"}, {"readings": ["のうどう"], "meanings": ["activity"], "word": "能動"}, {"readings": ["のうどうてき"], "meanings": ["active"], "word": "能動的"}, {"readings": ["はどう"], "meanings": ["wave motion", "undulation", "surge", "wave"], "word": "波動"}, {"readings": ["はつどう"], "meanings": ["putting into operation", "invocation"], "word": "発動"}, {"readings": ["はんどう"], "meanings": ["reaction", "recoil", "kick", "backlash"], "word": "反動"}, {"readings": ["ふどう"], "meanings": ["immovable", "motionless", "firm", "unwavering", "unshakable", "steadfast", "Acala (Wisdom King)", "Fudō", "fierce Buddhist deity"], "word": "不動"}, {"readings": ["ふどうさん"], "meanings": ["real estate"], "word": "不動産"}, {"readings": ["ふどうさんや"], "meanings": ["real estate agent", "realtor"], "word": "不動産屋"}, {"readings": ["ふどう"], "meanings": ["floating"], "word": "浮動"}, {"readings": ["へんどう"], "meanings": ["change", "fluctuation"], "word": "変動"}, {"readings": ["ぼうどう"], "meanings": ["insurrection", "rebellion", "revolt", "riot", "uprising"], "word": "暴動"}, {"readings": ["やくどう"], "meanings": ["lively motion", "throb"], "word": "躍動"}, {"readings": ["りゅうどう"], "meanings": ["flow"], "word": "流動"}, {"readings": ["りゅうどうてき"], "meanings": ["fluid", "unsettled"], "word": "流動的"}, {"readings": ["れんどう"], "meanings": ["operating together", "working together", "gearing", "linkage", "linked", "coupled", "interlocking"], "word": "連動"}, {"readings": ["ろうどううんどう"], "meanings": ["labour movement", "labor movement"], "word": "労働運動"}, {"readings": ["どうせい"], "meanings": ["state (of affairs)", "condition", "developments", "movements"], "word": "動静"}, {"readings": ["べつどうたい"], "meanings": ["flying column", "detached force"], "word": "別動隊"}, {"readings": ["けいじどうしゃ"], "meanings": ["light motor vehicle (up to 660cc and 64bhp)", "k-car", "kei car"], "word": "軽自動車"}, {"readings": ["りゅうどうしょく"], "meanings": ["liquid food (diet)"], "word": "流動食"}, {"readings": ["うんどうぐつ"], "meanings": ["sports shoes", "sneakers"], "word": "運動靴"}, {"readings": ["しゃかいうんどう"], "meanings": ["social movement"], "word": "社会運動"}, {"readings": ["どうぶつせい"], "meanings": ["animal (in nature)", "animal (in origin)"], "word": "動物性"}, {"readings": ["みうごき"], "meanings": ["moving about", "stirring about"], "word": "身動き"}, {"readings": ["そうどういん"], "meanings": ["general mobilization", "general mobilisation"], "word": "総動員"}, {"readings": ["びどう"], "meanings": ["slight movement", "slight tremor", "quiver"], "word": "微動"}, {"readings": ["じどうせいぎょ"], "meanings": ["automatic control"], "word": "自動制御"}, {"readings": ["ふどうかぶ"], "meanings": ["floating stock"], "word": "浮動株"}, {"readings": ["ふどうひょう"], "meanings": ["swing vote"], "word": "浮動票"}, {"readings": ["さくどう"], "meanings": ["maneuvers", "manoeuvers", "machinations", "scheming"], "word": "策動"}, {"readings": ["だいどうみゃく"], "meanings": ["aorta", "important traffic route"], "word": "大動脈"}, {"readings": ["せんきょうんどう"], "meanings": ["election campaign", "political campaign", "campaigning", "electioneering", "canvassing"], "word": "選挙運動"}, {"readings": ["いどうせいこうきあつ"], "meanings": ["migratory anticyclone"], "word": "移動性高気圧"}, {"readings": ["うごきだす"], "meanings": ["to come alive", "to get going", "to start to move"], "word": "動き出す"}, {"readings": ["クラブかつどう"], "meanings": ["club activities (usu. clubs in association with a school)", "extracurricular activities"], "word": "クラブ活動"}, {"readings": ["いどうへいきん"], "meanings": ["moving average"], "word": "移動平均"}]}