{"literal": "口", "radical": 30, "grade": 1, "jouyou": true, "strokeCount": 3, "on": ["コウ", "ク"], "kun": ["くち"], "meanings": ["mouth"], "compounds": [{"readings": ["いくどうおん"], "meanings": ["(saying) with one voice", "unanimously", "in chorus", "in unison", "as one"], "word": "異口同音"}, {"readings": ["ひとくち"], "meanings": ["mouthful", "morsel", "bite", "gulp", "sip", "draft", "draught", "one word", "in short", "one share", "one contribution"], "word": "一口"}, {"readings": ["かげぐち"], "meanings": ["malicious gossip", "backbiting", "speaking ill behind someone's back"], "word": "陰口"}, {"readings": ["かいさつぐち"], "meanings": ["ticket barrier", "ticket gate", "wicket"], "word": "改札口"}, {"readings": ["かいこう"], "meanings": ["opening", "aperture (e.g. camera)", "opening one's mouth", "beginning to speak", "open", "broad"], "word": "開口"}, {"readings": ["あまくち"], "meanings": ["sweet flavour", "sweet flavor", "mildness", "flattery", "stupidity"], "word": "甘口"}, {"readings": ["まぐち"], "meanings": ["frontage", "width (of a building, plot of land, etc.)", "breadth (e.g. of one's knowledge)", "scope (e.g. of one's work)", "range"], "word": "間口"}, {"readings": ["けいこう"], "meanings": ["taken by mouth", "oral"], "word": "経口"}, {"readings": ["かるくち"], "meanings": ["talkative", "loose-lipped", "persiflage", "frivolous talk"], "word": "軽口"}, {"readings": ["とぐち"], "meanings": ["door", "doorway"], "word": "戸口"}, {"readings": ["かたりくち"], "meanings": ["way of reciting", "way of telling a story"], "word": "語り口"}, {"readings": ["くち"], "meanings": ["mouth", "opening", "hole", "gap", "orifice", "mouth (of a bottle)", "spout", "nozzle", "mouthpiece", "gate", "door", "entrance", "exit", "speaking", "speech", "talk (i.e. gossip)", "taste", "palate", "mouth (to feed)", "opening (i.e. vacancy)", "available position", "invitation", "summons", "kind", "sort", "type", "opening (i.e. beginning)", "counter for mouthfuls, shares (of money), and swords"], "word": "口"}, {"readings": ["くちずさむ"], "meanings": ["to hum (a tune)", "to sing to oneself", "to croon"], "word": "口ずさむ"}, {"readings": ["くちコミ"], "meanings": ["word of mouth", "comments written online (about a product, service, etc.)", "online reviews"], "word": "口コミ"}, {"readings": ["くちび"], "meanings": ["fuse", "pilot light", "cause (of a war, argument, revolt, etc.)", "origin", "trigger"], "word": "口火"}, {"readings": ["こうかく"], "meanings": ["corners of the mouth"], "word": "口角"}, {"readings": ["くちがね"], "meanings": ["(metal) cap", "clasp", "mouthpiece", "socket (for light, etc.)"], "word": "口金"}, {"readings": ["こうけい"], "meanings": ["aperture", "bore", "calibre", "caliber"], "word": "口径"}, {"readings": ["こうご"], "meanings": ["spoken language", "colloquial speech", "(modern) spoken Japanese", "written style based on (modern) spoken Japanese"], "word": "口語"}, {"readings": ["くちべに"], "meanings": ["lipstick"], "word": "口紅"}, {"readings": ["こうざ"], "meanings": ["account (e.g. bank)"], "word": "口座"}, {"readings": ["くちどめ"], "meanings": ["forbidding to speak", "muzzling (a person)", "bribing into secrecy", "hush money"], "word": "口止め"}, {"readings": ["こうじつ"], "meanings": ["excuse", "pretext"], "word": "口実"}, {"readings": ["こうしゅう"], "meanings": ["bad breath", "halitosis"], "word": "口臭"}, {"readings": ["くちだし"], "meanings": ["interference", "meddling", "butting in"], "word": "口出し"}, {"readings": ["こうじゅつ"], "meanings": ["dictation", "verbal statement"], "word": "口述"}, {"readings": ["こうじょう"], "meanings": ["vocal message", "speech", "statement", "prologue at the start of a kabuki performance"], "word": "口上"}, {"readings": ["くちぶり"], "meanings": ["way of speaking", "intimation"], "word": "口ぶり"}, {"readings": ["くちきり"], "meanings": ["start broaching (a subject)", "opening remark", "start", "commencement", "beginning", "event at the start of the tenth month of the lunar calendar", "opening a sealed jar or container"], "word": "口切り"}, {"readings": ["くどく"], "meanings": ["to persuade", "to coax", "to solicit", "to seduce", "to make advances", "to make a play", "to make a pass", "to put the moves on", "to come on to", "to hit on", "to court", "to woo", "to romance"], "word": "口説く"}, {"readings": ["くちさき"], "meanings": ["lip service", "mere words", "professions", "lips", "mouth", "snout", "proboscis"], "word": "口先"}, {"readings": ["くちばしる"], "meanings": ["to blurt out", "to let slip", "to say inadvertently", "to come out with (e.g. nonsense)"], "word": "口走る"}, {"readings": ["こうちゅう"], "meanings": ["interior of the mouth", "oral cavity"], "word": "口中"}, {"readings": ["くちょう"], "meanings": ["tone (e.g. of voice, etc.)", "(verbal) expression"], "word": "口調"}, {"readings": ["くちぶえ"], "meanings": ["whistle (sound made with the lips)"], "word": "口笛"}, {"readings": ["くちあたり"], "meanings": ["taste", "smooth talking", "reception", "hospitality"], "word": "口当たり"}, {"readings": ["くちごたえ"], "meanings": ["retort", "back talk", "backchat"], "word": "口答え"}, {"readings": ["こうとう"], "meanings": ["oral", "verbal", "spoken", "parol"], "word": "口頭"}, {"readings": ["こうないえん"], "meanings": ["mouth ulcer", "stomatitis"], "word": "口内炎"}, {"readings": ["くちぐせ"], "meanings": ["pet saying", "favorite phrase (favorite)", "stock phrase", "manner of talking"], "word": "口癖"}, {"readings": ["くちやくそく"], "meanings": ["verbal promise", "one's word"], "word": "口約束"}, {"readings": ["くちきき"], "meanings": ["mediation", "good offices", "intervention", "mediator", "middleman", "influential person", "person of influence", "eloquence", "eloquent person", "way of speaking"], "word": "口利き"}, {"readings": ["くちごもる"], "meanings": ["to hesitate to say", "to mumble", "to hem and haw", "to falter"], "word": "口ごもる"}, {"readings": ["こうろん"], "meanings": ["quarrel", "argument", "row", "(verbal) dispute"], "word": "口論"}, {"readings": ["こうこう"], "meanings": ["pithead", "minehead"], "word": "坑口"}, {"readings": ["いとぐち"], "meanings": ["beginning", "start", "first step", "clue", "lead", "hint", "thread end"], "word": "糸口"}, {"readings": ["じゃぐち"], "meanings": ["faucet", "tap"], "word": "蛇口"}, {"readings": ["てぐち"], "meanings": ["modus operandi", "criminal technique", "trick"], "word": "手口"}, {"readings": ["あきぐち"], "meanings": ["beginning of autumn", "beginning of fall"], "word": "秋口"}, {"readings": ["じゅうこう"], "meanings": ["gun point", "muzzle"], "word": "銃口"}, {"readings": ["でぐち"], "meanings": ["exit", "gateway", "way out", "outlet", "vent", "leak"], "word": "出口"}, {"readings": ["じょのくち"], "meanings": ["the beginning (as in \"this is only the beginning\")", "lowest division in sumo"], "word": "序の口"}, {"readings": ["きずぐち"], "meanings": ["(opening of) a wound", "(mouth of a) wound", "cut"], "word": "傷口"}, {"readings": ["じんこう"], "meanings": ["population", "common talk"], "word": "人口"}, {"readings": ["にしぐち"], "meanings": ["west entrance"], "word": "西口"}, {"readings": ["きりくち"], "meanings": ["cut end", "section", "opening", "slit", "point of view", "(different) perspective", "new approach"], "word": "切り口"}, {"readings": ["はやくち"], "meanings": ["fast-talking", "rapid talking"], "word": "早口"}, {"readings": ["まどぐち"], "meanings": ["counter", "window", "teller window", "ticket window", "contact person", "point of contact"], "word": "窓口"}, {"readings": ["たきぐち"], "meanings": ["top of a waterfall"], "word": "滝口"}, {"readings": ["ちょこ"], "meanings": ["sake cup", "small deep porcelain bowl for serving food"], "word": "猪口"}, {"readings": ["ひがしぐち"], "meanings": ["east entrance"], "word": "東口"}, {"readings": ["はたらきぐち"], "meanings": ["position", "job", "employment", "opening"], "word": "働き口"}, {"readings": ["みなみぐち"], "meanings": ["south entrance"], "word": "南口"}, {"readings": ["ひじょうぐち"], "meanings": ["emergency exit"], "word": "非常口"}, {"readings": ["へいこう"], "meanings": ["dumbfounded", "stumped", "at one's wits' end", "nonplussed", "annoyed"], "word": "閉口"}, {"readings": ["きたぐち"], "meanings": ["north entrance"], "word": "北口"}, {"readings": ["むくち"], "meanings": ["taciturn", "reticent", "quiet", "silent", "untalkative"], "word": "無口"}, {"readings": ["りこう"], "meanings": ["clever", "intelligent", "wise", "bright", "sharp", "sensible", "smart", "shrewd", "well-behaved (esp. children and pets)", "obedient", "good", "good (with words)"], "word": "利口"}, {"readings": ["うらぐち"], "meanings": ["backdoor", "rear entrance", "unauthorized", "illicit", "illegal"], "word": "裏口"}, {"readings": ["わるぐち", "わるくち", "あっこう"], "meanings": ["slander", "bad-mouthing", "abuse", "insult", "speaking ill (of)"], "word": "悪口"}, {"readings": ["かこう", "かわぐち"], "meanings": ["mouth of river", "estuary"], "word": "河口"}, {"readings": ["こうこう"], "meanings": ["oral cavity", "mouth"], "word": "口腔"}, {"readings": ["くちかず"], "meanings": ["number of words a person speaks", "number of dependents", "number of mouths to feed", "number of shares, items, applications, etc."], "word": "口数"}, {"readings": ["いりぐち"], "meanings": ["entrance", "entry", "gate", "approach", "mouth"], "word": "入口"}, {"readings": ["くちぐち"], "meanings": ["every person", "every mouth", "every entrance"], "word": "口々"}, {"readings": ["くちぐちに"], "meanings": ["each and every person (saying)", "one and all", "unanimously", "in unison", "separately", "individually"], "word": "口々に"}, {"readings": ["でいりぐち"], "meanings": ["exit and entrance"], "word": "出入り口"}, {"readings": ["からくち"], "meanings": ["dry taste (e.g. sake, wine)", "a liking for sake", "one who likes sake", "salty (taste)", "harsh", "scathing"], "word": "辛口"}, {"readings": ["くちげんか"], "meanings": ["quarrel", "dispute", "argument"], "word": "口げんか"}, {"readings": ["こうとうべんろん"], "meanings": ["oral proceedings", "oral pleadings"], "word": "口頭弁論"}, {"readings": ["こぐち"], "meanings": ["cut end", "edge (of a page, etc.)", "small amount", "small quantity", "small sum", "beginning", "clue", "tiger's den", "jaws of death", "dangerous place"], "word": "小口"}, {"readings": ["おおぐち"], "meanings": ["big mouth", "mouth opened wide", "boastful speech", "tall talk", "bragging", "boasting", "large amount", "large quantity"], "word": "大口"}, {"readings": ["とりくち"], "meanings": ["technique", "techniques"], "word": "取り口"}, {"readings": ["こうとうしもん"], "meanings": ["oral examination", "interview"], "word": "口頭試問"}, {"readings": ["こうじょうがき"], "meanings": ["verbal note (notes verbale)", "written statement"], "word": "口上書"}, {"readings": ["くちぞえ"], "meanings": ["recommendation", "putting in a good word for someone"], "word": "口添え"}, {"readings": ["くちうら"], "meanings": ["determining a speaker's true or hidden meaning", "determining a speaker's intentions from his manner of speech", "divining good or bad luck from listening to someone"], "word": "口裏"}, {"readings": ["うすくち"], "meanings": ["light (flavor)", "lightly-seasoned", "thin (porcelain, paper, etc.)", "thinly made", "fine", "delicate", "thin soy sauce", "light soy sauce"], "word": "薄口"}, {"readings": ["かってぐち"], "meanings": ["kitchen door", "back door", "service door", "tradesman's entrance", "host's entrance to a tea-ceremony room"], "word": "勝手口"}, {"readings": ["ひぐち"], "meanings": ["burner", "nozzle", "origin of a fire"], "word": "火口"}, {"readings": ["みずぐち"], "meanings": ["spout"], "word": "水口"}, {"readings": ["でんわぐち"], "meanings": ["telephone receiver", "telephone mouthpiece", "making a telephone call", "receiving a telephone call"], "word": "電話口"}, {"readings": ["くちうるさい"], "meanings": ["nagging", "faultfinding", "carping", "captious"], "word": "口うるさい"}, {"readings": ["こうざばんごう"], "meanings": ["account number (bank, etc.)"], "word": "口座番号"}]}