{"literal": "味", "radical": 30, "grade": 3, "jouyou": true, "strokeCount": 8, "on": ["ミ"], "kun": ["あじ", "あじ.わう"], "meanings": ["flavor", "taste"], "compounds": [{"readings": ["いみ"], "meanings": ["meaning", "significance", "sense"], "word": "意味"}, {"readings": ["いみあい"], "meanings": ["implication", "nuance", "shade of meaning", "connotation"], "word": "意味合い"}, {"readings": ["いちみ"], "meanings": ["clan", "partisans", "conspirators", "gang", "ring", "crew", "participation (e.g. in a plot)", "one flavour", "one charm", "one ingredient (in traditional Chinese medicine)", "universality (of the teachings of Buddha)"], "word": "一味"}, {"readings": ["しおあじ"], "meanings": ["salty taste", "saltiness"], "word": "塩味"}, {"readings": ["かみ"], "meanings": ["seasoning", "flavoring", "flavouring", "addition", "inclusion", "taking into account"], "word": "加味"}, {"readings": ["かんみりょう"], "meanings": ["sweetener (sugar, honey, saccharin, maltose, etc.)", "sweetening agent", "sweetening"], "word": "甘味料"}, {"readings": ["きみ"], "meanings": ["sensation", "feeling", "tendency", "propensity"], "word": "気味"}, {"readings": ["きょうみ"], "meanings": ["interest (in something)", "curiosity (about something)", "zest (for)"], "word": "興味"}, {"readings": ["きょうみぶかい"], "meanings": ["very interesting", "of great interest"], "word": "興味深い"}, {"readings": ["ぎんみ"], "meanings": ["close examination", "careful selection", "testing", "scrutiny", "examination of criminal charges", "reciting and appreciating traditional poetry"], "word": "吟味"}, {"readings": ["にがみ"], "meanings": ["bitterness", "bitter taste"], "word": "苦味"}, {"readings": ["あとあじ"], "meanings": ["aftertaste"], "word": "後味"}, {"readings": ["こうみ"], "meanings": ["smell and taste", "flavour", "flavor"], "word": "香味"}, {"readings": ["さんみ"], "meanings": ["sourness", "acidity"], "word": "酸味"}, {"readings": ["しゅみ"], "meanings": ["hobby", "pastime", "tastes", "preference", "liking"], "word": "趣味"}, {"readings": ["こきみ"], "meanings": ["sentiment", "feeling"], "word": "小気味"}, {"readings": ["こきみよい"], "meanings": ["delightful", "satisfying", "gratifying", "brisk", "piquant"], "word": "小気味良い"}, {"readings": ["しょうみ"], "meanings": ["relish", "gusto", "appreciation"], "word": "賞味"}, {"readings": ["しんみ"], "meanings": ["fresh taste", "novelty", "originality", "freshness"], "word": "新味"}, {"readings": ["にんげんみ"], "meanings": ["human kindness", "human weakness"], "word": "人間味"}, {"readings": ["にんじょうみ"], "meanings": ["human interest", "kindness"], "word": "人情味"}, {"readings": ["しょうみ"], "meanings": ["net weight", "useful part", "actual content", "real", "effective", "full"], "word": "正味"}, {"readings": ["だいごみ"], "meanings": ["the real pleasure (of something)", "the real thrill", "the true charm", "flavour of ghee", "delicious taste", "Buddha's gracious teachings"], "word": "醍醐味"}, {"readings": ["じみ"], "meanings": ["plain", "simple", "subdued", "sober", "reserved (behaviour, attitude, etc.)", "modest", "quiet", "unobtrusive", "quite", "a (little) bit"], "word": "地味"}, {"readings": ["ちょうみりょう"], "meanings": ["seasoning", "flavoring", "flavouring", "condiment"], "word": "調味料"}, {"readings": ["ちんみ"], "meanings": ["delicacy", "dainties"], "word": "珍味"}, {"readings": ["びみ"], "meanings": ["good flavor", "good flavour", "delicacy", "dainty"], "word": "美味"}, {"readings": ["おいしい"], "meanings": ["delicious", "tasty", "sweet", "attractive", "appealing", "convenient", "favorable", "desirable", "profitable"], "word": "美味しい"}, {"readings": ["ぶきみ"], "meanings": ["weird", "ominous", "eerie", "uncanny", "ghastly"], "word": "不気味"}, {"readings": ["まずい"], "meanings": ["bad (taste)", "unpalatable", "unsavoury", "unsavory", "awful", "terrible", "unpleasant", "poor", "unskillful", "unskilful", "bungling", "clumsy", "ugly", "unattractive", "homely", "plain", "awkward", "problematic", "troublesome", "unfavorable", "unfavourable", "unwise"], "word": "不味い"}, {"readings": ["あじ"], "meanings": ["flavor", "flavour", "taste", "charm", "appeal", "uniqueness", "attractiveness", "experience", "taste (e.g. of victory)", "smart", "clever", "witty", "strange"], "word": "味"}, {"readings": ["あじつけ"], "meanings": ["seasoning", "flavour", "flavor"], "word": "味付け"}, {"readings": ["あじのもと"], "meanings": ["Ajinomoto", "brand name of monosodium glutamate (MSG)"], "word": "味の素"}, {"readings": ["あじわい"], "meanings": ["flavour", "flavor", "taste", "charm", "appeal", "interest", "meaning", "significance"], "word": "味わい"}, {"readings": ["あじわう"], "meanings": ["to taste", "to savor", "to savour", "to relish", "to appreciate", "to enjoy", "to relish", "to digest", "to experience", "to go through", "to taste (e.g. victory)", "to know (e.g. pain)"], "word": "味わう"}, {"readings": ["みかく"], "meanings": ["taste", "palate", "sense of taste"], "word": "味覚"}, {"readings": ["みそ"], "meanings": ["miso", "fermented condiment usu. made from soybeans", "innards (from crabs, shrimps, etc.) resembling miso", "key (main) point", "good part (of something)", "weakling", "weak person", "try"], "word": "味噌"}, {"readings": ["みそしる"], "meanings": ["miso soup"], "word": "味噌汁"}, {"readings": ["みかた"], "meanings": ["friend", "ally", "supporter", "taking sides with", "supporting", "standing by", "backing up"], "word": "味方"}, {"readings": ["みょうみ"], "meanings": ["exquisiteness", "charm", "beauty", "nice point", "advantage", "profit", "gain"], "word": "妙味"}, {"readings": ["むいみ"], "meanings": ["nonsense", "no meaning", "meaningless"], "word": "無意味"}, {"readings": ["やくみ"], "meanings": ["condiment (e.g. grated or chopped topping such as daikon, wasabi, ginger, green onion, red pepper)", "spice"], "word": "薬味"}, {"readings": ["しゃみせん"], "meanings": ["shamisen", "samisen", "three-stringed Japanese lute"], "word": "三味線"}, {"readings": ["あじけない"], "meanings": ["wearisome", "insipid", "dull", "irksome", "wretched", "vain"], "word": "味気ない"}, {"readings": ["きょうみしんしん"], "meanings": ["very interesting", "of absorbing interest", "having a keen interest (in)", "being immensely curious (about)"], "word": "興味津々"}, {"readings": ["きれあじ"], "meanings": ["sharpness", "cutting ability", "quickness (of wit)", "incisiveness", "technical proficiency", "skill", "peppiness (of a ball)"], "word": "切れ味"}, {"readings": ["あまみ"], "meanings": ["sweetness", "sugary taste", "sweets", "dessert", "cake"], "word": "甘味"}, {"readings": ["ちょうみ"], "meanings": ["seasoning", "flavoring", "flavouring"], "word": "調味"}, {"readings": ["ふうみ"], "meanings": ["taste", "flavor", "flavour"], "word": "風味"}, {"readings": ["もちあじ"], "meanings": ["inherent flavor", "inherent flavour", "natural taste", "distinctive characteristic (of a person, work, etc.)", "peculiar quality", "special ability"], "word": "持ち味"}, {"readings": ["むみ"], "meanings": ["tasteless", "flavourless", "uninteresting", "dull", "dry", "insipid"], "word": "無味"}, {"readings": ["したあじ"], "meanings": ["seasoning of food"], "word": "下味"}, {"readings": ["おおあじ"], "meanings": ["flat-tasting", "bland", "lacking in flavor", "dull", "flat", "unimaginative", "boring"], "word": "大味"}, {"readings": ["ぎみ"], "meanings": ["-like", "-looking", "-looked", "tending to ..."], "word": "気味"}, {"readings": ["かがくちょうみりょう"], "meanings": ["chemical seasoning (esp. monosodium glutamate)"], "word": "化学調味料"}, {"readings": ["いみづける"], "meanings": ["to give meaning to"], "word": "意味付ける"}, {"readings": ["しんじつみ"], "meanings": ["truth (veracity, authenticity) (e.g. of a report)"], "word": "真実味"}, {"readings": ["あるいみで"], "meanings": ["in a sense", "in some way", "to an extent"], "word": "ある意味で"}, {"readings": ["あるいみでは"], "meanings": ["in a sense", "in some way", "to an extent"], "word": "ある意味では"}, {"readings": ["いみふめい"], "meanings": ["of uncertain meaning", "ambiguous", "cryptic", "nonsensical", "incomprehensible", "perplexing"], "word": "意味不明"}, {"readings": ["ひとあじちがう"], "meanings": ["to be somewhat different (from before, from others, etc.)"], "word": "一味違う"}]}