{"literal": "明", "radical": 72, "grade": 2, "jouyou": true, "strokeCount": 8, "on": ["メイ", "ミョウ", "ミン"], "kun": ["あ.かり", "あか.るい", "あか.るむ", "あか.らむ", "あき.らか", "あ.ける", "-あ.け", "あ.く", "あ.くる", "あ.かす"], "meanings": ["bright", "light"], "compounds": [{"readings": ["めいはく"], "meanings": ["obvious", "clear", "plain", "evident", "apparent", "explicit", "overt"], "word": "明白"}, {"readings": ["かいめい"], "meanings": ["elucidation", "explication", "explaining", "unravelling", "clarification", "understanding"], "word": "解明"}, {"readings": ["かいめい"], "meanings": ["civilization", "civilisation", "enlightenment"], "word": "開明"}, {"readings": ["きゅうめい"], "meanings": ["investigation (esp. in academic and scientific contexts)"], "word": "究明"}, {"readings": ["けんめい"], "meanings": ["wise", "sensible", "well-advised", "intelligent", "sagacious", "prudent"], "word": "賢明"}, {"readings": ["げんめい"], "meanings": ["declaration", "statement", "assertion"], "word": "言明"}, {"readings": ["こうみょう"], "meanings": ["bright light", "hope", "bright future", "light emanating from a buddha or bodhisattva, symbolizing their wisdom and compassion"], "word": "光明"}, {"readings": ["こうめい"], "meanings": ["fairness", "openness", "impartiality", "Komeito (Japanese political party)"], "word": "公明"}, {"readings": ["こうめいせいだい"], "meanings": ["fair", "just and upright", "open and honest", "aboveboard", "honourable"], "word": "公明正大"}, {"readings": ["ゆくえふめい"], "meanings": ["missing", "lost", "unaccounted for", "whereabouts unknown"], "word": "行方不明"}, {"readings": ["こくめい"], "meanings": ["detailed", "scrupulous", "careful", "minute", "faithful", "elaborate", "diligent", "honest", "upright", "sincere"], "word": "克明"}, {"readings": ["じめい"], "meanings": ["self-evident", "obvious", "axiomatic", "self-explanatory", "trivial"], "word": "自明"}, {"readings": ["しつめい"], "meanings": ["loss of eyesight", "loss of vision", "going blind", "blindness"], "word": "失明"}, {"readings": ["しゃくめい"], "meanings": ["explanation", "vindication"], "word": "釈明"}, {"readings": ["しょうめい"], "meanings": ["illumination", "lighting"], "word": "照明"}, {"readings": ["しょうめい"], "meanings": ["proof", "verification", "certification"], "word": "証明"}, {"readings": ["しょうめいしょ"], "meanings": ["certificate (usually of proof of something)", "credentials"], "word": "証明書"}, {"readings": ["みぶんしょうめいしょ"], "meanings": ["identification papers", "ID", "piece of identification", "identity document"], "word": "身分証明書"}, {"readings": ["せいめい"], "meanings": ["pure and clear", "\"clear and bright\" solar term (approx. April 5)"], "word": "清明"}, {"readings": ["せいめい"], "meanings": ["declaration", "statement", "proclamation"], "word": "声明"}, {"readings": ["せつめい"], "meanings": ["explanation", "exposition"], "word": "説明"}, {"readings": ["せつめいしょ"], "meanings": ["(printed) instructions", "manual", "explanatory leaflet (pamphlet, note)", "description"], "word": "説明書"}, {"readings": ["せんめい"], "meanings": ["vivid", "clear", "distinct"], "word": "鮮明"}, {"readings": ["てんめい"], "meanings": ["dawn", "daybreak", "Tenmei era (1781.4.2-1789.1.25)"], "word": "天明"}, {"readings": ["とうめい"], "meanings": ["transparent", "clear"], "word": "透明"}, {"readings": ["としあけ"], "meanings": ["beginning of the year", "early in the New Year"], "word": "年明け"}, {"readings": ["としあける"], "meanings": ["the New Year dawns"], "word": "年明ける"}, {"readings": ["はつめい"], "meanings": ["invention", "intelligent", "clever", "smart", "making sense (of something)", "understanding"], "word": "発明"}, {"readings": ["はんめい"], "meanings": ["establishing", "proving", "ascertaining", "identifying", "confirming"], "word": "判明"}, {"readings": ["ひょうめい"], "meanings": ["declaration", "indication", "representation", "manifestation", "demonstration", "expression", "announcement", "assertion"], "word": "表明"}, {"readings": ["ふせんめい"], "meanings": ["blur", "blurred", "indistinct"], "word": "不鮮明"}, {"readings": ["ふとうめい"], "meanings": ["opaque", "obscure", "murky", "turbid", "opacity", "obscurity", "unclear", "unpredictable", "uncertain"], "word": "不透明"}, {"readings": ["ふめい"], "meanings": ["unclear", "obscure", "indistinct", "uncertain", "ambiguous", "unknown", "unidentified", "ignorance", "lack of wisdom", "lack of insight"], "word": "不明"}, {"readings": ["ぶんめい"], "meanings": ["civilization", "civilisation", "culture", "Bunmei era (1469.4.28-1487.7.20)"], "word": "文明"}, {"readings": ["へいめい"], "meanings": ["clear", "simple"], "word": "平明"}, {"readings": ["べんめい"], "meanings": ["explanation", "excuse", "clarification", "vindication", "apology"], "word": "弁明"}, {"readings": ["みめい"], "meanings": ["early dawn", "grey of morning", "gray of morning"], "word": "未明"}, {"readings": ["あかす"], "meanings": ["to pass (the night)", "to spend", "to reveal", "to divulge", "to disclose", "to expose", "to prove", "to verify"], "word": "明かす"}, {"readings": ["あくる"], "meanings": ["next (day, morning, etc.)", "following"], "word": "明くる"}, {"readings": ["あけわたす"], "meanings": ["to vacate", "to surrender (e.g. a castle)", "to give up (e.g. a position)", "to hand over (e.g. power)"], "word": "明け渡す"}, {"readings": ["あけがた"], "meanings": ["dawn"], "word": "明け方"}, {"readings": ["あきらか"], "meanings": ["clear", "obvious", "evident", "plain", "definite", "bright", "light"], "word": "明らか"}, {"readings": ["あかるい"], "meanings": ["light", "well-lit", "well-lighted", "bright (of a colour)", "brightly-coloured", "brightly-colored", "cheerful", "bright", "spirited", "sunny (e.g. disposition)", "encouraging (for the future of a project, etc.)", "promising", "of fair prospects", "familiar (with)", "knowledgeable (about)", "well versed (in)", "fair (e.g. politics)", "clean", "impartial"], "word": "明るい"}, {"readings": ["めいあん"], "meanings": ["light and darkness", "light and shade"], "word": "明暗"}, {"readings": ["めいかい"], "meanings": ["clear understanding"], "word": "明解"}, {"readings": ["めいかい"], "meanings": ["clear", "clear-cut", "lucid", "unequivocal", "explicit"], "word": "明快"}, {"readings": ["めいかく"], "meanings": ["clear", "precise", "definite", "distinct"], "word": "明確"}, {"readings": ["めいき"], "meanings": ["clear writing", "specification"], "word": "明記"}, {"readings": ["めいげん"], "meanings": ["declaration", "statement"], "word": "明言"}, {"readings": ["めいさい"], "meanings": ["details", "particulars", "specifics", "detailed", "minute", "detailed statement"], "word": "明細"}, {"readings": ["めいじ"], "meanings": ["elucidation", "explicit statement", "specification"], "word": "明示"}, {"readings": ["みょうじょう"], "meanings": ["morning star", "Venus", "preeminent person (within their own field)", "star (of the stage, silver screen, etc.)"], "word": "明星"}, {"readings": ["みょうちょう"], "meanings": ["tomorrow morning"], "word": "明朝"}, {"readings": ["みょうばん"], "meanings": ["tomorrow evening"], "word": "明晩"}, {"readings": ["めいぶん"], "meanings": ["explicit statement (e.g. law)", "express provision"], "word": "明文"}, {"readings": ["めいりょう"], "meanings": ["clear", "plain", "distinct", "obvious", "evident", "articulate"], "word": "明瞭"}, {"readings": ["めいろう"], "meanings": ["cheerful", "bright", "clear", "clean", "honest", "fair"], "word": "明朗"}, {"readings": ["めいせき"], "meanings": ["clear", "distinct"], "word": "明晰"}, {"readings": ["よあけ"], "meanings": ["dawn", "daybreak"], "word": "夜明け"}, {"readings": ["れいめい"], "meanings": ["daybreak", "dawn", "gray of the morning (grey)", "dawn (of a new age)"], "word": "黎明"}, {"readings": ["あさって", "みょうごにち"], "meanings": ["day after tomorrow"], "word": "明後日"}, {"readings": ["あした", "あす", "みょうにち"], "meanings": ["tomorrow", "near future"], "word": "明日"}, {"readings": ["あかり"], "meanings": ["light", "illumination", "glow", "gleam", "lamp", "light"], "word": "明かり"}, {"readings": ["うちあける"], "meanings": ["to confide", "to reveal", "to disclose", "to lay bare", "to speak frankly", "to open (one's heart)"], "word": "打ち明ける"}, {"readings": ["しあさって"], "meanings": ["in three days' time", "two days after tomorrow"], "word": "明明後日"}, {"readings": ["しあさって"], "meanings": ["in three days' time", "two days after tomorrow"], "word": "明明後日"}, {"readings": ["そうめい"], "meanings": ["wise", "sagacious", "intelligent", "sensible"], "word": "聡明"}, {"readings": ["つゆあけ"], "meanings": ["end of the rainy season"], "word": "梅雨明け"}, {"readings": ["みょうねん"], "meanings": ["next year"], "word": "明年"}, {"readings": ["めいじ"], "meanings": ["Meiji era (1868.9.8-1912.7.30)"], "word": "明治"}, {"readings": ["えいめい"], "meanings": ["intelligent", "wise", "bright", "brilliant", "clear-sighted"], "word": "英明"}, {"readings": ["かんめい"], "meanings": ["terse", "concise", "simple and clear"], "word": "簡明"}, {"readings": ["こうめいとう"], "meanings": ["Komeito (Japanese political party)"], "word": "公明党"}, {"readings": ["たいまつ"], "meanings": ["torch (made of pine, bamboo, reed, etc.)", "flambeau", "torchlight"], "word": "松明"}, {"readings": ["しんめい"], "meanings": ["deity", "god", "Amaterasu (as an enshrined deity)"], "word": "神明"}, {"readings": ["うすあかり"], "meanings": ["dim light", "faint light", "half-light of early morning", "twilight"], "word": "薄明かり"}, {"readings": ["しゅうあけ"], "meanings": ["beginning of next week (usu. Monday)", "early next week"], "word": "週明け"}, {"readings": ["めいぶんか"], "meanings": ["stipulation", "stating clearly", "documenting in writing", "stating explicitly"], "word": "明文化"}, {"readings": ["あけくれ"], "meanings": ["morning and evening", "all the time"], "word": "明け暮れ"}, {"readings": ["はつめいか"], "meanings": ["inventor"], "word": "発明家"}, {"readings": ["ぶんめいかいか"], "meanings": ["civilization and enlightenment", "Japan's Westernization movement during the Meiji era (Westernisation)"], "word": "文明開化"}, {"readings": ["せつめいぶん"], "meanings": ["explanatory note"], "word": "説明文"}, {"readings": ["いみふめい"], "meanings": ["of uncertain meaning", "ambiguous", "cryptic", "nonsensical", "incomprehensible", "perplexing"], "word": "意味不明"}]}