{"literal": "渋", "radical": 85, "grade": 8, "jouyou": true, "strokeCount": 11, "on": ["ジュウ", "シュウ"], "kun": ["しぶ", "しぶ.い", "しぶ.る"], "meanings": ["astringent", "hesitate", "reluctant", "have diarrhea"], "compounds": [{"readings": ["くじゅう"], "meanings": ["bitterness", "distress", "pain", "anguish", "affliction", "bitterness and astringency"], "word": "苦渋"}, {"readings": ["しぶい"], "meanings": ["astringent", "bitter", "puckery", "rough", "harsh", "tart", "austere", "elegant (and unobtrusive)", "refined", "quiet (and simple)", "sober", "sombre", "subdued", "tasteful (in a quiet way)", "understated", "sour (look)", "glum", "grim", "sullen", "sulky", "stingy", "tight-fisted"], "word": "渋い"}, {"readings": ["しぶる"], "meanings": ["to hesitate", "to hold back", "to balk", "to falter", "to be reluctant", "to be unwilling", "to begrudge", "to have loose painful bowel movement", "to suffer from tenesmus"], "word": "渋る"}, {"readings": ["しぶがき"], "meanings": ["astringent persimmon"], "word": "渋柿"}, {"readings": ["じゅうたい"], "meanings": ["congestion (e.g. traffic)", "delay", "stagnation"], "word": "渋滞"}, {"readings": ["なんじゅう"], "meanings": ["suffering", "distress", "difficulty", "hardship", "misery", "being bogged down", "hurdle"], "word": "難渋"}, {"readings": ["じゅうめん"], "meanings": ["grimace", "sullen face"], "word": "渋面"}, {"readings": ["しぶしぶ"], "meanings": ["reluctantly", "unwillingly"], "word": "渋々"}, {"readings": ["しぶ"], "meanings": ["astringent (puckery) juice (of unripe persimmons)"], "word": "渋"}, {"readings": ["しぶりばら"], "meanings": ["bowel pains", "painful loose bowels"], "word": "渋り腹"}]}