{"literal": "納", "radical": 120, "grade": 6, "jouyou": true, "strokeCount": 10, "on": ["ノウ", "ナッ", "ナ", "ナン", "トウ"], "kun": ["おさ.める", "-おさ.める", "おさ.まる"], "meanings": ["settlement", "obtain", "reap", "pay", "supply", "store"], "compounds": [{"readings": ["えんのう"], "meanings": ["deferred payment"], "word": "延納"}, {"readings": ["かくのう"], "meanings": ["storage", "housing for equipment and machines", "putting into computer memory"], "word": "格納"}, {"readings": ["かくのうこ"], "meanings": ["(aircraft) hangar"], "word": "格納庫"}, {"readings": ["ゆいのう"], "meanings": ["engagement gift", "(ceremonial) exchange of engagement gifts"], "word": "結納"}, {"readings": ["しゅうのう"], "meanings": ["storage", "putting or stowing away", "receipt (of funds, payment, etc.)", "harvesting"], "word": "収納"}, {"readings": ["すいとう"], "meanings": ["receipts and expenditure (disbursements)"], "word": "出納"}, {"readings": ["すいとうぼ"], "meanings": ["cashbook"], "word": "出納簿"}, {"readings": ["じょうのう"], "meanings": ["payment to the government"], "word": "上納"}, {"readings": ["たいのう"], "meanings": ["falling behind (with a payment)", "being in arrears", "non-payment", "default", "delinquency"], "word": "滞納"}, {"readings": ["なや"], "meanings": ["shed", "barn", "outhouse"], "word": "納屋"}, {"readings": ["のうかい"], "meanings": ["the last meeting (of the year, the term, etc.)"], "word": "納会"}, {"readings": ["のうき"], "meanings": ["appointed day of delivery", "time for payment"], "word": "納期"}, {"readings": ["のうぜい"], "meanings": ["payment of taxes"], "word": "納税"}, {"readings": ["なっとう"], "meanings": ["natto (fermented soybeans)"], "word": "納豆"}, {"readings": ["なっとく"], "meanings": ["consent", "assent", "agreement", "understanding", "comprehension", "grasp"], "word": "納得"}, {"readings": ["のうにゅう"], "meanings": ["payment (taxes, fees, etc.)", "supply (of goods)", "delivery"], "word": "納入"}, {"readings": ["のうひん"], "meanings": ["delivery of goods"], "word": "納品"}, {"readings": ["のうふ"], "meanings": ["payment", "supply"], "word": "納付"}, {"readings": ["ほうのう"], "meanings": ["dedication", "offering", "presentation", "oblation"], "word": "奉納"}, {"readings": ["みのう"], "meanings": ["payment default", "overdue on a payment"], "word": "未納"}, {"readings": ["へんのう"], "meanings": ["returning (to the authorities)", "restoring"], "word": "返納"}, {"readings": ["かのう"], "meanings": ["accepting with pleasure"], "word": "嘉納"}, {"readings": ["のうこつ"], "meanings": ["placing (a person's) ashes inside a funerary urn (or a tomb or ossuary)", "depositing ashes"], "word": "納骨"}, {"readings": ["なんど"], "meanings": ["storage room", "storeroom", "closet", "grayish blue"], "word": "納戸"}, {"readings": ["ぶつのう"], "meanings": ["payment in kind"], "word": "物納"}, {"readings": ["のうさい"], "meanings": ["betrothal gift"], "word": "納采"}, {"readings": ["のうきん"], "meanings": ["payment"], "word": "納金"}, {"readings": ["のうりょう"], "meanings": ["(enjoying the) cool of the evening"], "word": "納涼"}]}