{"literal": "鑑", "radical": 167, "grade": 8, "jouyou": true, "strokeCount": 23, "on": ["カン"], "kun": ["かんが.みる", "かがみ"], "meanings": ["specimen", "take warning from", "learn from"], "compounds": [{"readings": ["いんかん"], "meanings": ["stamp", "seal"], "word": "印鑑"}, {"readings": ["かんしき"], "meanings": ["judgement", "judgment", "discernment", "discrimination", "having an eye for", "appraisal (e.g. of an antique)", "evaluation", "assessment", "forensics", "(criminal) identification", "crime lab"], "word": "鑑識"}, {"readings": ["かんしょう"], "meanings": ["appreciation (of art, music, poetry, etc.)"], "word": "鑑賞"}, {"readings": ["かんてい"], "meanings": ["judgement", "judgment", "expert opinion", "appraisal"], "word": "鑑定"}, {"readings": ["かんべつ"], "meanings": ["discrimination", "judgement", "judgment", "separation", "sorting"], "word": "鑑別"}, {"readings": ["ずかん"], "meanings": ["pictorial book", "picture book", "illustrated reference book", "identification manual", "field guide"], "word": "図鑑"}, {"readings": ["ねんかん"], "meanings": ["yearbook", "almanac", "annual"], "word": "年鑑"}, {"readings": ["めいかん"], "meanings": ["directory", "list"], "word": "名鑑"}, {"readings": ["せいしんかんてい"], "meanings": ["psychiatric examination"], "word": "精神鑑定"}]}