{"literal": "変", "radical": 34, "grade": 4, "jouyou": true, "strokeCount": 9, "on": ["ヘン"], "kun": ["か.わる", "か.わり", "か.える"], "meanings": ["unusual", "change", "strange"], "compounds": [{"readings": ["いへん"], "meanings": ["unusual event", "strange occurrence", "strange phenomenon", "something abnormal", "change (for the worse)", "accident", "disaster"], "word": "異変"}, {"readings": ["うつりかわり"], "meanings": ["change (e.g. season)"], "word": "移り変わり"}, {"readings": ["いっぺん"], "meanings": ["complete change", "about-face"], "word": "一変"}, {"readings": ["かへん"], "meanings": ["variable", "changeable", "convertible", "controllable"], "word": "可変"}, {"readings": ["かいへん"], "meanings": ["change", "alteration", "modification"], "word": "改変"}, {"readings": ["かんこうへん"], "meanings": ["cirrhosis of the liver"], "word": "肝硬変"}, {"readings": ["きゅうへん"], "meanings": ["sudden turn", "sudden change", "(suddenly occurring) accident", "emergency"], "word": "急変"}, {"readings": ["じへん"], "meanings": ["accident", "disaster", "incident", "uprising", "emergency"], "word": "事変"}, {"readings": ["こころがわり"], "meanings": ["change of heart", "change of mind", "change in love interest"], "word": "心変わり"}, {"readings": ["せいへん"], "meanings": ["political disturbance", "political change", "change of government", "political upheaval", "overthrowing of a government", "coup d'état", "coup", "revolution"], "word": "政変"}, {"readings": ["あいかわらず"], "meanings": ["as ever", "as usual", "the same", "still"], "word": "相変わらず"}, {"readings": ["たいへん"], "meanings": ["very", "greatly", "terribly", "awfully", "immense", "enormous", "great", "serious", "grave", "dreadful", "terrible", "difficult", "hard", "major incident", "disaster"], "word": "大変"}, {"readings": ["ちかくへんどう"], "meanings": ["diastrophism", "movement and deformation of the earth's crust", "upheaval (e.g. in politics)", "seismic shift", "earthshaking changes"], "word": "地殻変動"}, {"readings": ["てんぺんちい"], "meanings": ["natural disaster", "cataclysm"], "word": "天変地異"}, {"readings": ["とつぜんへんい"], "meanings": ["mutation"], "word": "突然変異"}, {"readings": ["ふへん"], "meanings": ["eternal", "everlasting", "unchangeable", "immutable", "immovable", "constant", "permanent", "indestructible", "invariant"], "word": "不変"}, {"readings": ["へん"], "meanings": ["strange", "odd", "peculiar", "weird", "curious", "queer", "eccentric", "funny", "suspicious", "fishy", "unexpected", "change", "incident", "disturbance", "disaster", "accident", "flat"], "word": "変"}, {"readings": ["かえる"], "meanings": ["to change", "to alter", "to transform", "to convert", "to turn", "to vary", "to reform", "to revise", "to amend"], "word": "変える"}, {"readings": ["へんじる"], "meanings": ["to change into", "to be transformed", "to be transfigured", "to transform", "to alter", "to convert"], "word": "変じる"}, {"readings": ["かわった"], "meanings": ["another", "different", "various", "particular", "unusual", "novel", "peculiar"], "word": "変わった"}, {"readings": ["かわらない"], "meanings": ["constant", "invariant"], "word": "変わらない"}, {"readings": ["かわり"], "meanings": ["change", "alteration", "difference", "distinction", "something wrong", "abnormality", "unusual event", "accident", "incident"], "word": "変わり"}, {"readings": ["かわりはてる"], "meanings": ["to be completely changed"], "word": "変わり果てる"}, {"readings": ["かわりもの"], "meanings": ["eccentric", "oddball", "character", "weirdo"], "word": "変わり者"}, {"readings": ["かわりめ"], "meanings": ["turning point", "change", "transition", "turn (of the tide, century, etc.)", "point of difference"], "word": "変わり目"}, {"readings": ["かわる"], "meanings": ["to change", "to be transformed", "to be altered", "to vary", "to move to", "to be different", "to be uncommon", "to be unusual"], "word": "変わる"}, {"readings": ["へんい"], "meanings": ["variation", "rogue (something)"], "word": "変異"}, {"readings": ["へんい"], "meanings": ["change", "alteration", "transmutation", "mutation"], "word": "変移"}, {"readings": ["へんか"], "meanings": ["change", "variation", "alteration", "mutation", "transition", "transformation", "transfiguration", "metamorphosis", "variety", "diversity", "inflection", "declension", "conjugation", "sidestepping"], "word": "変化"}, {"readings": ["へんかきゅう"], "meanings": ["breaking ball (pitch)", "curve ball", "screwball"], "word": "変化球"}, {"readings": ["へんかく"], "meanings": ["change", "transformation", "innovation", "reform", "revolution", "revolutionizing", "upheaval", "Reformation"], "word": "変革"}, {"readings": ["へんかん"], "meanings": ["change", "conversion", "transformation", "transformation"], "word": "変換"}, {"readings": ["へんけい"], "meanings": ["transformation", "variation", "metamorphosis", "modification", "deformation", "variety", "deformity", "monster"], "word": "変形"}, {"readings": ["へんげん"], "meanings": ["transformation"], "word": "変幻"}, {"readings": ["へんこう"], "meanings": ["change", "modification", "alteration", "revision", "amendment"], "word": "変更"}, {"readings": ["へんし"], "meanings": ["unnatural death", "accidental death", "violent death"], "word": "変死"}, {"readings": ["へんしつ"], "meanings": ["alteration (of character or essence)", "change in quality", "transformation", "deterioration", "degeneration", "transmutation"], "word": "変質"}, {"readings": ["へんしょく"], "meanings": ["change of color", "change of colour", "fading", "discoloration", "discolouration"], "word": "変色"}, {"readings": ["へんしん"], "meanings": ["change of mind", "inconstancy", "apostasy"], "word": "変心"}, {"readings": ["へんしん"], "meanings": ["metamorphosis", "disguise", "transformation", "shapeshifting", "morphing"], "word": "変身"}, {"readings": ["へんじん"], "meanings": ["eccentric", "crank", "oddball"], "word": "変人"}, {"readings": ["へんすう"], "meanings": ["variable"], "word": "変数"}, {"readings": ["へんせい"], "meanings": ["denaturation", "degeneration"], "word": "変性"}, {"readings": ["へんせつ"], "meanings": ["betrayal", "defection", "treachery", "apostasy"], "word": "変節"}, {"readings": ["へんせん"], "meanings": ["change", "transition", "vicissitudes"], "word": "変遷"}, {"readings": ["へんそうきょく"], "meanings": ["variation"], "word": "変奏曲"}, {"readings": ["へんそう"], "meanings": ["disguise", "masquerade"], "word": "変装"}, {"readings": ["へんぞう"], "meanings": ["alteration", "defacement", "debasement", "falsification", "forgery"], "word": "変造"}, {"readings": ["へんそく"], "meanings": ["irregularity", "anomaly"], "word": "変則"}, {"readings": ["へんそく"], "meanings": ["shifting gears", "changing gears"], "word": "変速"}, {"readings": ["へんたい"], "meanings": ["transformation", "abnormality", "sexual perversion", "pervert", "metamorphosis", "transformation", "transition", "modification"], "word": "変態"}, {"readings": ["へんちょう"], "meanings": ["change of tone", "variation (music)", "irregularity", "anomaly", "abnormality", "modulation (in radio)"], "word": "変調"}, {"readings": ["へんでんしょ"], "meanings": ["transformer substation"], "word": "変電所"}, {"readings": ["へんどう"], "meanings": ["change", "fluctuation"], "word": "変動"}, {"readings": ["へんぼう"], "meanings": ["transfiguration", "transformation", "change of appearance"], "word": "変貌"}, {"readings": ["へんよう"], "meanings": ["change in appearance", "transformation"], "word": "変容"}, {"readings": ["りんきおうへん"], "meanings": ["adapting oneself to the requirements of the moment", "playing by ear", "ad hoc approach"], "word": "臨機応変"}, {"readings": ["かわりだね"], "meanings": ["something out of the ordinary", "variant", "variety", "exception", "novelty", "person with an unusual character or background", "unique figure", "exceptional type", "eccentric", "oddball"], "word": "変わり種"}, {"readings": ["げきへん"], "meanings": ["sudden change", "upheaval"], "word": "激変"}, {"readings": ["へんてん"], "meanings": ["mutation", "change", "transition"], "word": "変転"}, {"readings": ["びょうへん"], "meanings": ["lesion", "pathological change"], "word": "病変"}, {"readings": ["さまがわり"], "meanings": ["changing completely", "transformation"], "word": "様変わり"}, {"readings": ["かわりみ"], "meanings": ["change of attitude (stance, position)", "lightness of foot", "ability to dodge out of the way of an attack"], "word": "変わり身"}, {"readings": ["へんてつ"], "meanings": ["something unusual", "something odd", "something out of the ordinary"], "word": "変哲"}, {"readings": ["ふうがわり"], "meanings": ["strange", "eccentric"], "word": "風変わり"}, {"readings": ["はやがわり"], "meanings": ["quick change", "quick transformation", "metamorphosis", "turning suddenly into"], "word": "早変わり"}, {"readings": ["うつりかわる"], "meanings": ["to change"], "word": "移り変わる"}, {"readings": ["かえ"], "meanings": ["changing", "change"], "word": "変え"}, {"readings": ["へんこうとどけ"], "meanings": ["notification of change", "alteration report", "registration of modification"], "word": "変更届"}]}