{"literal": "屋", "radical": 44, "grade": 3, "jouyou": true, "strokeCount": 9, "on": ["オク"], "kun": ["や"], "meanings": ["roof", "house", "shop", "dealer", "seller"], "compounds": [{"readings": ["パンや"], "meanings": ["bakery", "baker", "pastry shop"], "word": "パン屋"}, {"readings": ["おくがい"], "meanings": ["outdoors", "outside"], "word": "屋外"}, {"readings": ["やごう"], "meanings": ["name of store", "trade name (esp. of a sole proprietorship)", "stage name (e.g. of actor)"], "word": "屋号"}, {"readings": ["やね"], "meanings": ["roof"], "word": "屋根"}, {"readings": ["おくじょう"], "meanings": ["rooftop"], "word": "屋上"}, {"readings": ["やたい"], "meanings": ["cart (esp. a food cart)", "stall", "stand", "festival float", "portable shrine dedicated to a god and shaped like a house", "dancing platform", "stage prop fashioned after a large building", "framework (of a house, etc.)", "house (esp. a small and miserable house)"], "word": "屋台"}, {"readings": ["おくない"], "meanings": ["indoor (court, pool, etc.)"], "word": "屋内"}, {"readings": ["おろしどんや"], "meanings": ["wholesaler"], "word": "卸問屋"}, {"readings": ["かおく"], "meanings": ["house", "building"], "word": "家屋"}, {"readings": ["はなや"], "meanings": ["florist", "flower shop"], "word": "花屋"}, {"readings": ["かしや"], "meanings": ["confectionery shop", "candy store", "sweet shop"], "word": "菓子屋"}, {"readings": ["がくや"], "meanings": ["dressing room", "green room", "backstage", "behind the scenes", "the inside", "inside affairs"], "word": "楽屋"}, {"readings": ["いわや"], "meanings": ["cavern", "grotto"], "word": "岩屋"}, {"readings": ["いざかや"], "meanings": ["izakaya", "Japanese bar that also serves various dishes and snacks"], "word": "居酒屋"}, {"readings": ["さかなや"], "meanings": ["fish market", "fish dealer"], "word": "魚屋"}, {"readings": ["くつや"], "meanings": ["shoe store", "shoe shop", "shoemaker"], "word": "靴屋"}, {"readings": ["ふるほんや"], "meanings": ["secondhand bookshop", "secondhand bookstore", "secondhand bookseller"], "word": "古本屋"}, {"readings": ["つくりざかや"], "meanings": ["sake brewer", "sake brewery"], "word": "造り酒屋"}, {"readings": ["ころしや"], "meanings": ["professional killer", "hit man"], "word": "殺し屋"}, {"readings": ["やまごや"], "meanings": ["hut (esp. on a mountain)", "shack", "refuge", "shanty"], "word": "山小屋"}, {"readings": ["しちや"], "meanings": ["pawnshop"], "word": "質屋"}, {"readings": ["しばいごや"], "meanings": ["playhouse", "theatre", "theater"], "word": "芝居小屋"}, {"readings": ["しゃしんや"], "meanings": ["photo studio", "photographer", "camera shop", "photography supplies shop", "photo processing shop", "photo finishing shop"], "word": "写真屋"}, {"readings": ["さかや"], "meanings": ["liquor store", "wine shop", "bottle shop", "sake dealer", "liquor-store owner", "brewer"], "word": "酒屋"}, {"readings": ["やどや"], "meanings": ["inn"], "word": "宿屋"}, {"readings": ["こや"], "meanings": ["hut", "cabin", "shed", "(animal) pen", "small theatre (theater)", "temporary playhouse", "circus tent", "booth", "one's own house"], "word": "小屋"}, {"readings": ["しょうや"], "meanings": ["village headman (esp. in the Kansai region)"], "word": "庄屋"}, {"readings": ["とこや"], "meanings": ["barbershop", "barber shop", "barber"], "word": "床屋"}, {"readings": ["てれや"], "meanings": ["shy", "a very shy person"], "word": "照れ屋"}, {"readings": ["そうかいや"], "meanings": ["extortionist that threatens to disrupt stock-holder meetings"], "word": "総会屋"}, {"readings": ["ちゃや"], "meanings": ["teahouse", "(Edo period) rest stop", "(geisha) teahouse", "establishment where patrons are entertained by geisha", "tea house (that sells tea)", "tea dealer"], "word": "茶屋"}, {"readings": ["しまりや"], "meanings": ["thrifty person", "stingy person", "tight-fisted person"], "word": "締まり屋"}, {"readings": ["どけんや"], "meanings": ["general (civil engineering and construction) contractor"], "word": "土建屋"}, {"readings": ["にくや"], "meanings": ["meat shop", "butcher's shop", "butcher"], "word": "肉屋"}, {"readings": ["なや"], "meanings": ["shed", "barn", "outhouse"], "word": "納屋"}, {"readings": ["やおや"], "meanings": ["greengrocer", "fruit and vegetable shop"], "word": "八百屋"}, {"readings": ["ふどうさんや"], "meanings": ["real estate agent", "realtor"], "word": "不動産屋"}, {"readings": ["へや"], "meanings": ["room", "chamber", "apartment", "flat", "pad", "stable"], "word": "部屋"}, {"readings": ["ふろや"], "meanings": ["public bathhouse", "bathhouse proprietor"], "word": "風呂屋"}, {"readings": ["わからずや"], "meanings": ["obstinate person", "blockhead"], "word": "分からず屋"}, {"readings": ["こめや"], "meanings": ["rice shop", "rice dealer"], "word": "米屋"}, {"readings": ["ほんや"], "meanings": ["bookstore", "bookshop", "publisher", "main building"], "word": "本屋"}, {"readings": ["りょうりや"], "meanings": ["restaurant"], "word": "料理屋"}, {"readings": ["こうや", "こんや"], "meanings": ["dyer"], "word": "紺屋"}, {"readings": ["とんや"], "meanings": ["wholesale store", "wholesale dealer", "wholesaler"], "word": "問屋"}, {"readings": ["おもや"], "meanings": ["main building (of a manor)", "central room (of a house)"], "word": "母屋"}, {"readings": ["のみや"], "meanings": ["bar", "saloon", "pub", "tavern", "drinking establishment"], "word": "飲み屋"}, {"readings": ["ひらや"], "meanings": ["bungalow", "one-story house"], "word": "平屋"}, {"readings": ["やしき"], "meanings": ["residence", "estate", "grounds", "premises", "mansion"], "word": "屋敷"}, {"readings": ["そばや"], "meanings": ["soba restaurant"], "word": "蕎麦屋"}, {"readings": ["やたいぼね"], "meanings": ["framework (of a building)", "foundation", "mainstay", "support", "supporter", "fortune"], "word": "屋台骨"}, {"readings": ["はいおく"], "meanings": ["dilapidated house", "deserted house"], "word": "廃屋"}, {"readings": ["しゃおく"], "meanings": ["company office building"], "word": "社屋"}, {"readings": ["てらこや"], "meanings": ["temple elementary school (during the Edo period)"], "word": "寺子屋"}, {"readings": ["かぶや"], "meanings": ["stockbroker"], "word": "株屋"}, {"readings": ["あいべや"], "meanings": ["sharing a room", "dormitory room", "match between wrestlers from the same stable"], "word": "相部屋"}, {"readings": ["おおべや"], "meanings": ["large room", "green room", "waiting room for performers when off stage", "junior actor", "actor of small parts", "large hospital room (for several patients)", "hospital ward", "ōbeya", "project management technique in manufacturing, involving group meetings in a common room"], "word": "大部屋"}, {"readings": ["ながや"], "meanings": ["tenement house", "row house"], "word": "長屋"}, {"readings": ["やかたぶね"], "meanings": ["houseboat", "pleasure boat (large, roofed)"], "word": "屋形船"}, {"readings": ["やねうら"], "meanings": ["attic", "loft"], "word": "屋根裏"}, {"readings": ["じんや"], "meanings": ["encampment"], "word": "陣屋"}, {"readings": ["だがしや"], "meanings": ["small-time candy store"], "word": "駄菓子屋"}, {"readings": ["なごや"], "meanings": ["Nagoya (city)"], "word": "名古屋"}]}