{"literal": "延", "radical": 54, "grade": 6, "jouyou": true, "strokeCount": 8, "on": ["エン"], "kun": ["の.びる", "の.べる", "の.べ", "の.ばす"], "meanings": ["prolong", "stretching"], "compounds": [{"readings": ["はびこる"], "meanings": ["to become overgrown", "to grow thick", "to spread", "to run rampant", "to thrive", "to prevail", "to become powerful"], "word": "蔓延る"}, {"readings": ["あつえん"], "meanings": ["rolling", "extending by applying pressure"], "word": "圧延"}, {"readings": ["うてんじゅんえん"], "meanings": ["rescheduled in case of rain"], "word": "雨天順延"}, {"readings": ["のべ"], "meanings": ["futures", "credit (buying)", "stretching", "total (preceding counter, unit, etc.)", "aggregate", "gross"], "word": "延べ"}, {"readings": ["えんき"], "meanings": ["postponement", "deferment", "adjournment"], "word": "延期"}, {"readings": ["えんしょう"], "meanings": ["spread of fire"], "word": "延焼"}, {"readings": ["えんたい"], "meanings": ["arrears", "(being) overdue", "delay (e.g. in payment)", "procrastination"], "word": "延滞"}, {"readings": ["えんちょう"], "meanings": ["extension", "elongation", "prolongation", "lengthening", "Enchō era (923.4.11-931.4.26)"], "word": "延長"}, {"readings": ["えんのう"], "meanings": ["deferred payment"], "word": "延納"}, {"readings": ["えんめい"], "meanings": ["keeping alive longer", "prolonging life", "life extension", "life-support"], "word": "延命"}, {"readings": ["くりのべ"], "meanings": ["postponement"], "word": "繰り延べ"}, {"readings": ["くりのべる"], "meanings": ["to postpone", "to defer", "to reschedule"], "word": "繰り延べる"}, {"readings": ["じゅんえん"], "meanings": ["postponement", "moving to a later date"], "word": "順延"}, {"readings": ["いきのびる"], "meanings": ["to survive", "to live long"], "word": "生き延びる"}, {"readings": ["ちえん"], "meanings": ["delay", "latency"], "word": "遅延"}, {"readings": ["まんえん"], "meanings": ["spread (e.g. of a disease)", "rampancy", "infestation", "proliferation", "being widespread"], "word": "蔓延"}, {"readings": ["えんえん"], "meanings": ["forever", "endlessly", "on and on", "meandering", "wandering", "winding", "sinuous", "serpentine", "zigzagging"], "word": "延々"}, {"readings": ["ひきのばす"], "meanings": ["to stretch larger", "to enlarge (photos)", "to delay (e.g. the end of a meeting)"], "word": "引き延ばす"}, {"readings": ["ねつえん"], "meanings": ["hot rolling"], "word": "熱延"}, {"readings": ["ひきのばし"], "meanings": ["extension", "prolongation", "enlargement"], "word": "引き延ばし"}]}