{"literal": "怠", "radical": 61, "grade": 8, "jouyou": true, "strokeCount": 9, "on": ["タイ"], "kun": ["おこた.る", "なま.ける"], "meanings": ["neglect", "laziness"], "compounds": [{"readings": ["だるい"], "meanings": ["sluggish", "languid", "listless", "heavy (heart, legs, etc.)", "dull", "bothersome", "tiresome", "pain-in-the-ass"], "word": "怠い"}, {"readings": ["けんたい"], "meanings": ["weariness", "fatigue", "languor", "boredom", "tedium", "ennui"], "word": "倦怠"}, {"readings": ["なまける"], "meanings": ["to be idle", "to slacken", "to neglect (e.g. one's work)"], "word": "怠ける"}, {"readings": ["なまけもの"], "meanings": ["lazy person", "lazy fellow", "slothful person"], "word": "怠け者"}, {"readings": ["おこたる"], "meanings": ["to be negligent in doing something", "to shirk", "to be off one's guard"], "word": "怠る"}, {"readings": ["たいだ"], "meanings": ["lazy", "idle", "indolent", "slothful"], "word": "怠惰"}, {"readings": ["たいまん"], "meanings": ["negligence", "neglect", "carelessness", "procrastination"], "word": "怠慢"}, {"readings": ["おこたり"], "meanings": ["negligence", "carelessness"], "word": "怠り"}]}