{"literal": "止", "radical": 77, "grade": 2, "jouyou": true, "strokeCount": 4, "on": ["シ"], "kun": ["と.まる", "-ど.まり", "と.める", "-と.める", "-ど.め", "とど.める", "とど.め", "とど.まる", "や.める", "や.む", "-や.む", "よ.す", "-さ.す", "-さ.し"], "meanings": ["stop", "halt"], "compounds": [{"readings": ["きゅうし"], "meanings": ["pause", "cessation", "rest"], "word": "休止"}, {"readings": ["きんし"], "meanings": ["prohibition", "inhibition", "ban"], "word": "禁止"}, {"readings": ["よびとめる"], "meanings": ["to (call and) stop", "to call (someone) to stop", "to hail (e.g. a taxi)"], "word": "呼び止める"}, {"readings": ["くちどめ"], "meanings": ["forbidding to speak", "muzzling (a person)", "bribing into secrecy", "hush money"], "word": "口止め"}, {"readings": ["さしとめ"], "meanings": ["prohibition", "ban", "suspension"], "word": "差し止め"}, {"readings": ["さんかぼうしざい"], "meanings": ["antioxidant"], "word": "酸化防止剤"}, {"readings": ["よす"], "meanings": ["to cease", "to desist", "to cut it out", "to lay off (an activity)", "to drop (a subject) to abolish", "to resign", "to give up"], "word": "止す"}, {"readings": ["とまる"], "meanings": ["to stop (moving)", "to come to a stop", "to stop (doing, working, being supplied)", "to come to a halt", "to cease", "to be stopped", "to be suspended", "to alight", "to perch on"], "word": "止まる"}, {"readings": ["やむ"], "meanings": ["to cease", "to stop", "to be over"], "word": "止む"}, {"readings": ["とめる"], "meanings": ["to stop", "to turn off", "to park", "to prevent", "to suppress (a cough)", "to hold back (tears)", "to hold (one's breath)", "to relieve (pain)", "to stop (someone from doing something)", "to dissuade", "to forbid", "to prohibit", "to notice", "to be aware of", "to concentrate on", "to pay attention to", "to remember", "to bear in mind", "to fix (in place)", "to fasten", "to tack", "to pin", "to nail", "to button", "to staple", "to detain", "to keep in custody"], "word": "止める"}, {"readings": ["やめる"], "meanings": ["to stop (an activity)", "to cease", "to discontinue", "to end", "to quit", "to cancel", "to abandon", "to give up", "to abolish", "to abstain", "to refrain"], "word": "止める"}, {"readings": ["しけつ"], "meanings": ["stopping of bleeding", "stanching", "hemostasis", "haemostasis"], "word": "止血"}, {"readings": ["はどめ"], "meanings": ["brake", "drag", "skid", "pawl", "restraint", "curtailment", "self-imposed limit", "check"], "word": "歯止め"}, {"readings": ["いとめる"], "meanings": ["to shoot dead", "to bring down (an animal)", "to win (a prize, someone's heart, etc.)", "to make one's own"], "word": "射止める"}, {"readings": ["うけとめる"], "meanings": ["to catch", "to stop the blow", "to react to", "to take (advice, etc.)", "to accept", "to come to grips with"], "word": "受け止める"}, {"readings": ["しゅうしふ"], "meanings": ["full stop", "period", "end"], "word": "終止符"}, {"readings": ["けしとめる"], "meanings": ["to put out", "to extinguish"], "word": "消し止める"}, {"readings": ["くいとめる"], "meanings": ["to check", "to hold back", "to keep at bay", "to stop", "to prevent", "to stem", "to curb", "to halt"], "word": "食い止める"}, {"readings": ["せいし"], "meanings": ["control", "check", "restraint", "inhibition"], "word": "制止"}, {"readings": ["せいし"], "meanings": ["stillness", "repose", "standing still"], "word": "静止"}, {"readings": ["そし"], "meanings": ["obstruction", "check", "hindrance", "prevention", "impediment", "interdiction", "preemption", "blocking"], "word": "阻止"}, {"readings": ["あしどめ"], "meanings": ["preventing (someone) from leaving", "confinement", "keeping indoors", "inducement to stay", "being stranded", "grounding", "level dyeing"], "word": "足止め"}, {"readings": ["ちゅうし"], "meanings": ["suspension", "stoppage", "discontinuance", "interruption"], "word": "中止"}, {"readings": ["つうこうどめ"], "meanings": ["closure (of a road)", "suspension of traffic", "road closed", "closed to traffic", "no through road"], "word": "通行止め"}, {"readings": ["ていし"], "meanings": ["stoppage", "coming to a stop", "halt", "standstill", "ceasing (movement, activity, etc.)", "suspension (of operations)", "interruption (e.g. of electricity supply)", "cutting off", "suspension (of payment, licence, etc.)", "(temporary) prohibition", "ban", "suspension of music, dance, etc. as a sign of mourning for a prominent person"], "word": "停止"}, {"readings": ["つきとめる"], "meanings": ["to determine (esp. a culprit or underlying cause)", "to pin down", "to ascertain", "to locate", "to identify", "to stab to death"], "word": "突き止める"}, {"readings": ["はとば"], "meanings": ["wharf", "quay", "landing-stage", "jetty"], "word": "波止場"}, {"readings": ["はいし"], "meanings": ["abolition", "repeal"], "word": "廃止"}, {"readings": ["ぼうし"], "meanings": ["prevention", "check"], "word": "防止"}, {"readings": ["よくし"], "meanings": ["check", "checkmate", "stave off", "control", "restraint", "inhibit", "deterrent", "deterrence"], "word": "抑止"}, {"readings": ["たちどまる"], "meanings": ["to stop (in one's tracks)", "to come to a stop", "to halt", "to pause", "to stand still"], "word": "立ち止まる"}, {"readings": ["いきどまり"], "meanings": ["dead end", "cul-de-sac", "blind alley", "no through road (i.e. on signage)", "end", "end of the road", "end point", "as far as one can go"], "word": "行き止まり"}, {"readings": ["うちとめる"], "meanings": ["to hammer into place", "to end (a performance)", "to kill", "to slay", "to shoot dead", "to cut down"], "word": "撃ち止める"}, {"readings": ["たちいりきんし"], "meanings": ["No Entry", "No Trespassing", "No Admittance", "Off Limits", "Keep Out", "Keep Off", "off-limits", "restricted", "forbidden"], "word": "立ち入り禁止"}, {"readings": ["ひきとめる"], "meanings": ["to detain", "to check", "to restrain"], "word": "引き止める"}, {"readings": ["とめどなく"], "meanings": ["endlessly", "ceaselessly"], "word": "止めどなく"}, {"readings": ["きんしほう"], "meanings": ["negative statute", "law against something"], "word": "禁止法"}, {"readings": ["すべりどめ"], "meanings": ["non-slip device (material, tread, etc.)", "non-skid", "anti-slip", "anti-skid", "taking an entrance examination to a (less desirable) university as a contingency in case one is rejected from one's first choice", "backup school", "safety school", "insurance choice"], "word": "滑り止め"}, {"readings": ["くるまどめ"], "meanings": ["(railway) buffer stop", "bumper", "bumping post"], "word": "車止め"}, {"readings": ["とまり"], "meanings": ["stop", "stoppage", "end"], "word": "止まり"}, {"readings": ["ひやけどめ"], "meanings": ["sunscreen", "suntan lotion", "sunblock"], "word": "日焼け止め"}, {"readings": ["しょうきゅうし"], "meanings": ["short break", "breather"], "word": "小休止"}, {"readings": ["うちどめ"], "meanings": ["end (of play, match, etc.)", "closing", "closing a pachinko machine (after it has paid out its designated maximum)"], "word": "打ち止め"}, {"readings": ["とどまる"], "meanings": ["to remain", "to abide", "to stay (in the one place)", "to be limited to", "to be confined to", "to only account for"], "word": "止まる"}, {"readings": ["きんしじこう"], "meanings": ["prohibited item", "banned item"], "word": "禁止事項"}]}