{"literal": "歴", "radical": 77, "grade": 4, "jouyou": true, "strokeCount": 14, "on": ["レキ", "レッキ"], "kun": [], "meanings": ["curriculum", "continuation", "passage of time"], "compounds": [{"readings": ["がくれき"], "meanings": ["academic background"], "word": "学歴"}, {"readings": ["けいれき"], "meanings": ["personal history", "career"], "word": "経歴"}, {"readings": ["しょくれき"], "meanings": ["work experience", "work history"], "word": "職歴"}, {"readings": ["ぜんれき"], "meanings": ["personal history"], "word": "前歴"}, {"readings": ["へんれき"], "meanings": ["travels", "pilgrimage", "itinerancy"], "word": "遍歴"}, {"readings": ["らいれき"], "meanings": ["history", "career"], "word": "来歴"}, {"readings": ["りれき"], "meanings": ["personal history", "background", "career", "log", "record", "history", "hysteresis"], "word": "履歴"}, {"readings": ["りれきしょ"], "meanings": ["personal history", "curriculum vitae", "resume"], "word": "履歴書"}, {"readings": ["りゃくれき"], "meanings": ["brief personal record", "short curriculum vitae", "short CV"], "word": "略歴"}, {"readings": ["れきし"], "meanings": ["history"], "word": "歴史"}, {"readings": ["れきしてき"], "meanings": ["historic", "historical", "traditional"], "word": "歴史的"}, {"readings": ["れきせん"], "meanings": ["long military service", "having experienced many battles"], "word": "歴戦"}, {"readings": ["れきだい"], "meanings": ["successive generations", "successive emperors"], "word": "歴代"}, {"readings": ["れきにん"], "meanings": ["successive jobs", "consecutive jobs"], "word": "歴任"}, {"readings": ["れきほう"], "meanings": ["round of calls", "tour of visitation"], "word": "歴訪"}, {"readings": ["れきぜん"], "meanings": ["evident", "plain", "distinct", "clear"], "word": "歴然"}, {"readings": ["びょうれき"], "meanings": ["clinical (case) history"], "word": "病歴"}, {"readings": ["れきてい"], "meanings": ["a route or passage"], "word": "歴程"}, {"readings": ["せんれき"], "meanings": ["military service", "combat experience"], "word": "戦歴"}]}