{"literal": "燥", "radical": 86, "grade": 8, "jouyou": true, "strokeCount": 17, "on": ["ソウ"], "kun": ["はしゃ.ぐ"], "meanings": ["parch", "dry up"], "compounds": [{"readings": ["かんそう"], "meanings": ["dryness", "aridity", "drying (e.g. clothes)", "dehydration", "desiccation", "insipidity"], "word": "乾燥"}, {"readings": ["かんそうき"], "meanings": ["drying machine", "dryer", "desiccator"], "word": "乾燥機"}, {"readings": ["しょうそう"], "meanings": ["impatience", "uneasiness", "irritation", "fretfulness"], "word": "焦燥"}, {"readings": ["はしゃぐ"], "meanings": ["to make merry", "to frolic", "to be in high spirits"], "word": "燥ぐ"}]}