{"literal": "臨", "radical": 131, "grade": 6, "jouyou": true, "strokeCount": 18, "on": ["リン"], "kun": ["のぞ.む"], "meanings": ["look to", "face", "meet", "confront", "attend", "call on"], "compounds": [{"readings": ["くんりん"], "meanings": ["reigning", "controlling", "to reign", "to dictate", "to control"], "word": "君臨"}, {"readings": ["のぞむ"], "meanings": ["to look out on", "to overlook", "to front onto", "to face (a situation, crisis, etc.)", "to meet (e.g. death)", "to be confronted by", "to deal with (an issue)", "to attend (e.g. a function)", "to appear (e.g. in court)", "to be present at", "to take part in"], "word": "臨む"}, {"readings": ["りんかい"], "meanings": ["boundary", "(nuclear) criticality", "critical (mass, pressure, temperature, state, point, etc.)"], "word": "臨界"}, {"readings": ["りんきおうへん"], "meanings": ["adapting oneself to the requirements of the moment", "playing by ear", "ad hoc approach"], "word": "臨機応変"}, {"readings": ["りんげつ"], "meanings": ["last month of pregnancy"], "word": "臨月"}, {"readings": ["りんじ"], "meanings": ["temporary", "provisional", "interim", "special", "extraordinary", "extra"], "word": "臨時"}, {"readings": ["りんじゅう"], "meanings": ["deathbed", "dying hour", "one's death"], "word": "臨終"}, {"readings": ["りんしょう"], "meanings": ["clinical (e.g. pathology, physiology)"], "word": "臨床"}, {"readings": ["りんじょうかん"], "meanings": ["(sense of) presence", "realism", "ambiance"], "word": "臨場感"}, {"readings": ["りんこう"], "meanings": ["facing (along) the harbor (harbour)"], "word": "臨港"}, {"readings": ["りんけん"], "meanings": ["on-the-spot investigation or inspection", "raid"], "word": "臨検"}, {"readings": ["りんかい"], "meanings": ["coastal", "seaside", "oceanfront", "maritime"], "word": "臨海"}, {"readings": ["りんしょ"], "meanings": ["writing (from a copy)"], "word": "臨書"}, {"readings": ["りんせん"], "meanings": ["preparing for action or battle"], "word": "臨戦"}, {"readings": ["りんしょうい"], "meanings": ["clinician"], "word": "臨床医"}]}