{"literal": "試", "radical": 149, "grade": 4, "jouyou": true, "strokeCount": 13, "on": ["シ"], "kun": ["こころ.みる", "ため.す"], "meanings": ["test", "try", "attempt", "experiment", "ordeal"], "compounds": [{"readings": ["ためし"], "meanings": ["trial", "test"], "word": "試し"}, {"readings": ["ためす"], "meanings": ["to attempt", "to test", "to try out"], "word": "試す"}, {"readings": ["こころみ"], "meanings": ["attempt", "trial", "experiment", "endeavour (endeavor)", "effort", "venture", "initiative"], "word": "試み"}, {"readings": ["こころみる"], "meanings": ["to try", "to attempt", "to have a go (at something)"], "word": "試みる"}, {"readings": ["しあん"], "meanings": ["tentative plan", "draft plan"], "word": "試案"}, {"readings": ["しうんてん"], "meanings": ["trial run", "test run"], "word": "試運転"}, {"readings": ["しきんせき"], "meanings": ["touchstone", "Lydian stone", "touchstone (e.g. of success)", "test", "litmus test"], "word": "試金石"}, {"readings": ["しくつ"], "meanings": ["prospecting", "trial digging"], "word": "試掘"}, {"readings": ["しけん"], "meanings": ["examination", "exam", "test", "trial", "experiment", "test"], "word": "試験"}, {"readings": ["しけんかん"], "meanings": ["test tube"], "word": "試験管"}, {"readings": ["しこう"], "meanings": ["making an attempt", "trial run"], "word": "試行"}, {"readings": ["しこうさくご"], "meanings": ["trial and error"], "word": "試行錯誤"}, {"readings": ["しあい"], "meanings": ["match", "game", "bout", "contest"], "word": "試合"}, {"readings": ["しさく"], "meanings": ["trial manufacture", "experiment", "test piece", "prototype"], "word": "試作"}, {"readings": ["しさん"], "meanings": ["trial calculation", "preliminary calculation", "estimation"], "word": "試算"}, {"readings": ["ししゃ"], "meanings": ["preview", "private showing"], "word": "試写"}, {"readings": ["ししょく"], "meanings": ["sampling food"], "word": "試食"}, {"readings": ["しちゃく"], "meanings": ["trying on clothes"], "word": "試着"}, {"readings": ["しやく"], "meanings": ["reagent"], "word": "試薬"}, {"readings": ["しよう"], "meanings": ["trial", "experimental use"], "word": "試用"}, {"readings": ["しりょう"], "meanings": ["sample", "specimen", "test piece"], "word": "試料"}, {"readings": ["しれん"], "meanings": ["test", "trial", "probation", "ordeal", "tribulation"], "word": "試練"}, {"readings": ["にゅうがくしけん"], "meanings": ["entrance examination"], "word": "入学試験"}, {"readings": ["にゅうし"], "meanings": ["entrance examination"], "word": "入試"}, {"readings": ["ひっきしけん"], "meanings": ["written examination"], "word": "筆記試験"}, {"readings": ["もぎしけん"], "meanings": ["trial examination", "mock examination"], "word": "模擬試験"}, {"readings": ["ちからだめし"], "meanings": ["test of one's strength", "test of one's ability"], "word": "力試し"}, {"readings": ["かんぜんしあい"], "meanings": ["perfect game"], "word": "完全試合"}, {"readings": ["しじょう"], "meanings": ["test drive", "test ride", "trial ride"], "word": "試乗"}, {"readings": ["しけんじょう"], "meanings": ["examination hall", "examination room", "laboratory", "experimental station", "testing ground"], "word": "試験場"}, {"readings": ["こっかしけん"], "meanings": ["state examination"], "word": "国家試験"}, {"readings": ["こうとうしもん"], "meanings": ["oral examination", "interview"], "word": "口頭試問"}, {"readings": ["むしけん"], "meanings": ["without an examination"], "word": "無試験"}, {"readings": ["ししゃ"], "meanings": ["test firing"], "word": "試射"}, {"readings": ["しいん"], "meanings": ["sampling a drink", "tasting"], "word": "試飲"}, {"readings": ["しけんてき"], "meanings": ["experimental", "provisional"], "word": "試験的"}, {"readings": ["のうぎょうしけんじょう"], "meanings": ["agricultural experiment station"], "word": "農業試験場"}, {"readings": ["りんぎょうしけんじょう"], "meanings": ["experimental forestry station"], "word": "林業試験場"}, {"readings": ["ついし"], "meanings": ["supplementary examination"], "word": "追試"}, {"readings": ["もし"], "meanings": ["mock examination", "trial examination"], "word": "模試"}]}