{"literal": "陶", "radical": 170, "grade": 8, "jouyou": true, "strokeCount": 11, "on": ["トウ"], "kun": [], "meanings": ["pottery", "porcelain"], "compounds": [{"readings": ["とうき"], "meanings": ["porcelain (esp. soft-paste porcelain)", "china", "chinaware", "earthenware", "pottery", "ceramics", "crockery"], "word": "陶器"}, {"readings": ["とうげい"], "meanings": ["ceramic art", "ceramics"], "word": "陶芸"}, {"readings": ["とうこう"], "meanings": ["potter"], "word": "陶工"}, {"readings": ["とうじ"], "meanings": ["clay"], "word": "陶磁"}, {"readings": ["とうじき"], "meanings": ["porcelain", "china", "chinaware", "ceramics", "pottery"], "word": "陶磁器"}, {"readings": ["とうすい"], "meanings": ["intoxication", "being carried away by", "being enraptured by"], "word": "陶酔"}, {"readings": ["うっとうしい"], "meanings": ["gloomy (e.g. mood)", "depressing", "irritating", "troublesome", "heavy (weather)", "cloudy"], "word": "鬱陶しい"}, {"readings": ["せいとう"], "meanings": ["porcelain manufacturing"], "word": "製陶"}]}